pywisetransfer/__init__.py
pywisetransfer/account_details.py
pywisetransfer/balance_statements.py
pywisetransfer/balances.py
pywisetransfer/base.py
pywisetransfer/borderless_account.py
pywisetransfer/deprecation.py
pywisetransfer/endpoint.py
pywisetransfer/exceptions.py
pywisetransfer/keys.py
pywisetransfer/multi_currency_account.py
pywisetransfer/profile.py
pywisetransfer/signing.py
pywisetransfer/subscription.py
pywisetransfer/user.py
pywisetransfer/webhooks.py
pywisetransfer-0.3.4.2.dist-info/LICENSE
pywisetransfer-0.3.4.2.dist-info/METADATA
pywisetransfer-0.3.4.2.dist-info/WHEEL
pywisetransfer-0.3.4.2.dist-info/RECORD
