Metadata-Version: 2.3
Name: pywisetransfer
Version: 0.3.4.2
Summary: Python library for the TransferWise API
License: AGPL-3.0
Keywords: payments,transferwise
Author: James Addison
Author-email: jay@jp-hosting.net
Requires-Python: >3.9.1
Classifier: License :: OSI Approved :: GNU Affero General Public License v3
Classifier: Programming Language :: Python :: 3
Classifier: Programming Language :: Python :: 3.10
Classifier: Programming Language :: Python :: 3.11
Classifier: Programming Language :: Python :: 3.12
Classifier: Programming Language :: Python :: 3.13
Provides-Extra: dev
Requires-Dist: apiron (>=9.0.0,<10)
Requires-Dist: black (>=25.1.0,<26) ; extra == "dev"
Requires-Dist: cryptography (>=45.0.0,<46)
Requires-Dist: munch (>=4.0.0,<5)
Requires-Dist: munch-stubs (>=0.1.2,<0.2) ; extra == "dev"
Requires-Dist: pytest (>=8.3.4,<9) ; extra == "dev"
Requires-Dist: responses (>=0.25.0,<0.26) ; extra == "dev"
Requires-Dist: types-cryptography (>=3.3.23.2,<3.4) ; extra == "dev"
Project-URL: Homepage, https://www.github.com/jayaddison/pywisetransfer
Project-URL: Repository, https://www.github.com/jayaddison/pywisetransfer
